google_measurement_protocol/__init__.py
google_measurement_protocol/enhanced_purchase.py
google_measurement_protocol/event.py
google_measurement_protocol/pageview.py
google_measurement_protocol/report.py
google_measurement_protocol/transaction.py
google_measurement_protocol-1.1.0.dist-info/LICENSE
google_measurement_protocol-1.1.0.dist-info/METADATA
google_measurement_protocol-1.1.0.dist-info/WHEEL
google_measurement_protocol-1.1.0.dist-info/top_level.txt
google_measurement_protocol-1.1.0.dist-info/RECORD
